head_of_apache/__init__.py
head_of_apache/_version.py
head_of_apache/main.py
head_of_apache-0.1.1.dist-info/LICENSE
head_of_apache-0.1.1.dist-info/METADATA
head_of_apache-0.1.1.dist-info/WHEEL
head_of_apache-0.1.1.dist-info/entry_points.txt
head_of_apache-0.1.1.dist-info/top_level.txt
head_of_apache-0.1.1.dist-info/RECORD
